azure/mgmt/apimanagement/__init__.py
azure/mgmt/apimanagement/_api_management_client.py
azure/mgmt/apimanagement/_configuration.py
azure/mgmt/apimanagement/_patch.py
azure/mgmt/apimanagement/_serialization.py
azure/mgmt/apimanagement/_vendor.py
azure/mgmt/apimanagement/_version.py
azure/mgmt/apimanagement/py.typed
azure/mgmt/apimanagement/aio/__init__.py
azure/mgmt/apimanagement/aio/_api_management_client.py
azure/mgmt/apimanagement/aio/_configuration.py
azure/mgmt/apimanagement/aio/_patch.py
azure/mgmt/apimanagement/aio/_vendor.py
azure/mgmt/apimanagement/aio/operations/__init__.py
azure/mgmt/apimanagement/aio/operations/_api_diagnostic_operations.py
azure/mgmt/apimanagement/aio/operations/_api_export_operations.py
azure/mgmt/apimanagement/aio/operations/_api_issue_attachment_operations.py
azure/mgmt/apimanagement/aio/operations/_api_issue_comment_operations.py
azure/mgmt/apimanagement/aio/operations/_api_issue_operations.py
azure/mgmt/apimanagement/aio/operations/_api_management_client_operations.py
azure/mgmt/apimanagement/aio/operations/_api_management_operations_operations.py
azure/mgmt/apimanagement/aio/operations/_api_management_service_operations.py
azure/mgmt/apimanagement/aio/operations/_api_management_service_skus_operations.py
azure/mgmt/apimanagement/aio/operations/_api_management_skus_operations.py
azure/mgmt/apimanagement/aio/operations/_api_operation_operations.py
azure/mgmt/apimanagement/aio/operations/_api_operation_policy_operations.py
azure/mgmt/apimanagement/aio/operations/_api_operations.py
azure/mgmt/apimanagement/aio/operations/_api_policy_operations.py
azure/mgmt/apimanagement/aio/operations/_api_product_operations.py
azure/mgmt/apimanagement/aio/operations/_api_release_operations.py
azure/mgmt/apimanagement/aio/operations/_api_revision_operations.py
azure/mgmt/apimanagement/aio/operations/_api_schema_operations.py
azure/mgmt/apimanagement/aio/operations/_api_tag_description_operations.py
azure_mgmt_apimanagement-4.0.1.dist-info/LICENSE
azure_mgmt_apimanagement-4.0.1.dist-info/METADATA
azure_mgmt_apimanagement-4.0.1.dist-info/WHEEL
azure_mgmt_apimanagement-4.0.1.dist-info/top_level.txt
azure_mgmt_apimanagement-4.0.1.dist-info/RECORD
